{"packageId":"ecarmf.mag-audit-return-intelligence","name":"MAG Audit Return Intelligence","packageVersion":"1.0.0","publisher":"MAG Dynamics","dependencies":[{"packageId":"ecarmf.mag-audit-evidence","minimumVersion":"1.0.0"}],"entities":[{"entityTypeName":"CanonicalTaxFact","description":"Versioned tax fact with evidence provenance.","attributes":[{"name":"factId","dataType":"string","required":true},{"name":"caseId","dataType":"string","required":true},{"name":"concept","dataType":"string","required":true},{"name":"value","dataType":"number","required":false},{"name":"sourceArtifactId","dataType":"string","required":true}]}],"events":[{"eventName":"CanonicalTaxFactReceived"}],"rules":[],"capabilities":[{"capabilityId":"MagAuditReturnIntelligence","name":"Return Intelligence","description":"Recognition canonical facts strict line mapping and reconciliation."}],"workflows":[],"agents":[]}
